[
	{
		"city": "Brasov",
		"county": "Brasov",
		"email": "catena@gmail.com",
		"pharmacyId": 1,
		"phone": "0743 004 062",
		"street": "Gospodarilor 3",
		"postalCode": "500464"
	},
		{
		"city": "Brasov",
		"county": "Brasov",
		"email": "catena@gmail.com",
		"pharmacyId": 1,
		"phone": "0740 828 222",
		"street": "Stadionului 2",
		"postalCode": "500064"
	},
		{
		"city": "Brasov",
		"county": "Sacele",
		"email": "catena@gmail.com",
		"pharmacyId": 1,
		"phone": "0741 106 343",
		"street": "Stefan cel Mare 15",
		"postalCode": "505600"
	},
	{
		"city": "Brasov",
		"county": "Sacele",
		"email": "catena@gmail.com",
		"pharmacyId": 1,
		"phone": "0741 106 843",
		"street": "Piata Libertatii nr 30",
		"postalCode": "505600"
	},	
	{
		"city": "Brasov",
		"county": "Brasov",
		"email": "catena@gmail.com",
		"pharmacyId": 1,
		"phone": "0268 310 586",
		"street": "Bulevardul Victoriei 1-3",
		"postalCode": "500214"
	},	
	{
		"city": "Brasov",
		"county": "Brasov",
		"email": "farmacia_dona@gmail.com",
		"pharmacyId": 2,
		"phone": "0372 407 041",
		"street": "Spicului 7",
		"postalCode": "500460"
	},	
	{
		"city": "Brasov",
		"county": "Brasov",
		"email": "farmacia_dona@gmail.com",
		"pharmacyId": 2,
		"phone": "0372 407 175",
		"street": "Nicopole 65",
		"postalCode": "500058"
	},	
	{
		"city": "Brasov",
		"county": "Brasov",
		"email": "farmacia_dona@gmail.com",
		"pharmacyId": 2,
		"phone": "0372 407 192",
		"street": "13 Decembrie 117",
		"postalCode": "500146"
	},	
	{
		"city": "Brasov",
		"county": "Brasov",
		"email": "ecofarmacia@gmail.com",
		"pharmacyId": 3,
		"phone": "0268 547 198",
		"street": "Iuliu Maniu 68",
		"postalCode": "500091"
	},	
	{
		"city": "Brasov",
		"county": "Brasov",
		"email": "ecofarmacia@gmail.com",
		"pharmacyId": 3,
		"phone": "0268 310 684",
		"street": "Saturn 32",
		"postalCode": "500342"
	},	
	{
		"city": "Brasov",
		"county": "Brasov",
		"email": "drmax@gmail.com",
		"pharmacyId": 4,
		"phone": "0268 321 431",
		"street": "Strada Traian 4",
		"postalCode": "500332"
	},	
	{
		"city": "Brasov",
		"county": "Brasov",
		"email": "drmax@gmail.com",
		"pharmacyId": 4,
		"phone": "0725 679 027",
		"street": "Calea Bucuresti Nr 20",
		"postalCode": "500326"
	},	
	{
		"city": "Brasov",
		"county": "Brasov",
		"email": "sensiblu@gmail.com",
		"pharmacyId": 5,
		"phone": "0726 301 297",
		"street": "Avram Iancu Nr. 77",
		"postalCode": "500075"
	},	
	{
		"city": "Brasov",
		"county": "Brasov",
		"email": "mediafarm@gmail.com",
		"pharmacyId": 7,
		"phone": "0730 711 620",
		"street": "Iuliu Maniu Nr. 33",
		"postalCode": "500091"
	},
	{
		"city": "Brasov",
		"county": "Brasov",
		"email": "plafar@gmail.com",
		"pharmacyId": 5,
		"phone": "0730 711 220",
		"street": "Saturn 20",
		"postalCode": "500338"
	}	
]